mhacks1/__init__.py
mhacks1/testing1.py
mhacks1/use_openai.py
mhacks1-1.3.dist-info/LICENSE.txt
mhacks1-1.3.dist-info/METADATA
mhacks1-1.3.dist-info/WHEEL
mhacks1-1.3.dist-info/entry_points.txt
mhacks1-1.3.dist-info/top_level.txt
mhacks1-1.3.dist-info/RECORD
