Metadata-Version: 2.1
Name: mhacks1
Version: 1.3
Summary: mhacks devtools
Home-page: https://pypi.org/project/mhacks1
Author: aarham
Author-email: aarham.wasit@gmail.com
Classifier: Programming Language :: Python :: 3
Classifier: License :: OSI Approved :: MIT License
Classifier: Operating System :: OS Independent
Requires-Python: >=3.6
License-File: LICENSE.txt
Requires-Dist: openai
